QNPy/CNP_ARCHITECTURE.py
QNPy/CNP_DATASETCLASS.py
QNPy/CNP_METRICS.py
QNPy/Clustering_with_SOM.py
QNPy/PREDICTION.py
QNPy/PREDICTION_Original_mjd.py
QNPy/PREDICTION_onePDF.py
QNPy/PREDICTION_onePDF_original_mjd.py
QNPy/Preprocess.py
QNPy/SPLITTING_AND_TRAINING.py
QNPy/__init__.py
QNPy-0.0.2.dist-info/LICENSE
QNPy-0.0.2.dist-info/METADATA
QNPy-0.0.2.dist-info/WHEEL
QNPy-0.0.2.dist-info/top_level.txt
QNPy-0.0.2.dist-info/RECORD
