Metadata-Version: 2.1
Name: QNPy
Version: 0.0.2
Summary: Modeling Quasar time series with Neural processes in Python
Home-page: https://github.com/kittytheastronaut/QNPy
Author-email: marinapavlovic5812@gmail.com
Classifier: Programming Language :: Python :: 3
Classifier: License :: OSI Approved :: MIT License
Classifier: Operating System :: OS Independent
Requires-Python: >=3.7
License-File: LICENSE
